{
  "annotations": {
    "list": [
      {
        "builtIn": 1,
        "datasource": {
          "type": "grafana",
          "uid": "-- Grafana --"
        },
        "enable": true,
        "hide": true,
        "iconColor": "rgba(0, 211, 255, 1)",
        "name": "Annotations & Alerts",
        "type": "dashboard"
      }
    ]
  },
  "editable": true,
  "fiscalYearStartMonth": 0,
  "graphTooltip": 0,
  "id": null,
  "uid": "sensor-overview",
  "links": [],
  "liveNow": false,
  "panels": [
    {
      "type": "stat",
      "title": "Temperature (°C)",
      "gridPos": { "h": 6, "w": 8, "x": 0, "y": 0 },
      "targets": [
        {
          "datasource": { "type": "prometheus", "uid": "Prometheus" },
          "expr": "sensor_temperature_celsius",
          "legendFormat": "",
          "refId": "A"
        }
      ],
      "options": {
        "reduceOptions": { "calcs": ["lastNotNull"], "fields": "", "values": false },
        "orientation": "auto",
        "textMode": "auto",
        "colorMode": "value",
        "graphMode": "none",
        "justifyMode": "auto"
      },
      "fieldConfig": {
        "defaults": {
          "unit": "celsius",
          "mappings": [],
          "thresholds": {
            "mode": "absolute",
            "steps": [
              { "color": "green", "value": null },
              { "color": "orange", "value": 35 },
              { "color": "red", "value": 40 }
            ]
          }
        },
        "overrides": []
      }
    },
    {
      "type": "stat",
      "title": "Humidity (%)",
      "gridPos": { "h": 6, "w": 8, "x": 8, "y": 0 },
      "targets": [
        {
          "datasource": { "type": "prometheus", "uid": "Prometheus" },
          "expr": "sensor_humidity_percent",
          "legendFormat": "",
          "refId": "A"
        }
      ],
      "options": {
        "reduceOptions": { "calcs": ["lastNotNull"], "fields": "", "values": false },
        "orientation": "auto",
        "textMode": "auto",
        "colorMode": "value",
        "graphMode": "none",
        "justifyMode": "auto"
      },
      "fieldConfig": {
        "defaults": {
          "unit": "percent",
          "mappings": [],
          "thresholds": {
            "mode": "absolute",
            "steps": [
              { "color": "green", "value": null },
              { "color": "orange", "value": 70 },
              { "color": "red", "value": 85 }
            ]
          }
        },
        "overrides": []
      }
    },
    {
      "type": "timeseries",
      "title": "Temperature over time",
      "gridPos": { "h": 8, "w": 24, "x": 0, "y": 6 },
      "targets": [
        {
          "datasource": { "type": "prometheus", "uid": "Prometheus" },
          "expr": "sensor_temperature_celsius",
          "legendFormat": "Temperature",
          "refId": "A"
        }
      ],
      "fieldConfig": {
        "defaults": { "unit": "celsius" },
        "overrides": []
      },
      "options": {
        "legend": { "displayMode": "list", "placement": "bottom" },
        "tooltip": { "mode": "single" }
      }
    },
    {
      "type": "timeseries",
      "title": "Humidity over time",
      "gridPos": { "h": 8, "w": 24, "x": 0, "y": 14 },
      "targets": [
        {
          "datasource": { "type": "prometheus", "uid": "Prometheus" },
          "expr": "sensor_humidity_percent",
          "legendFormat": "Humidity",
          "refId": "A"
        }
      ],
      "fieldConfig": {
        "defaults": { "unit": "percent" },
        "overrides": []
      },
      "options": {
        "legend": { "displayMode": "list", "placement": "bottom" },
        "tooltip": { "mode": "single" }
      }
    },
    {
      "type": "stat",
      "title": "Last successful read",
      "gridPos": { "h": 4, "w": 8, "x": 0, "y": 22 },
      "targets": [
        {
          "datasource": { "type": "prometheus", "uid": "Prometheus" },
          "expr": "sensor_last_read_success_unix",
          "legendFormat": "",
          "refId": "A"
        }
      ],
      "fieldConfig": {
        "defaults": { "unit": "s" },
        "overrides": []
      }
    },
    {
      "type": "bargauge",
      "title": "Reads & Errors",
      "gridPos": { "h": 4, "w": 16, "x": 8, "y": 22 },
      "targets": [
        { "datasource": { "type": "prometheus", "uid": "Prometheus" }, "expr": "increase(sensor_reads_total[5m])", "refId": "A" },
        { "datasource": { "type": "prometheus", "uid": "Prometheus" }, "expr": "increase(sensor_read_errors_total[5m])", "refId": "B" }
      ],
      "options": {
        "displayMode": "gradient"
      }
    }
  ],
  "schemaVersion": 39,
  "style": "dark",
  "tags": ["sensors"],
  "templating": { "list": [] },
  "time": { "from": "now-6h", "to": "now" },
  "timepicker": {},
  "timezone": "",
  "title": "Sensor Overview",
  "version": 1
}


